{
  "updateTime": "2026-02-03T21:41:40.829Z",
  "updateTimeLocal": "2026/2/4 上午5:41:40",
  "currency": "TWD",
  "cryptos": [
    {
      "id": "bitcoin",
      "symbol": "BTC",
      "name": "Bitcoin",
      "icon": "₿",
      "price": 2405336,
      "priceUsd": 76359.87301587302,
      "change24h": -2.92595,
      "marketCap": 48088458897587,
      "volume24h": 2276891407392,
      "high24h": 2495199,
      "low24h": 2310958
    },
    {
      "id": "ethereum",
      "symbol": "ETH",
      "name": "Ethereum",
      "icon": "Ξ",
      "price": 72303,
      "priceUsd": 2295.3333333333335,
      "change24h": -2.16124,
      "marketCap": 8723725298975,
      "volume24h": 1458430883432,
      "high24h": 74298,
      "low24h": 66916
    },
    {
      "id": "binancecoin",
      "symbol": "BNB",
      "name": "BNB",
      "icon": "🔶",
      "price": 24181,
      "priceUsd": 767.6507936507936,
      "change24h": -1.02934,
      "marketCap": 3299317158024,
      "volume24h": 60355156384,
      "high24h": 24658,
      "low24h": 23288
    },
    {
      "id": "ripple",
      "symbol": "XRP",
      "name": "XRP",
      "icon": "✕",
      "price": 50.79,
      "priceUsd": 1.6123809523809522,
      "change24h": -0.87636,
      "marketCap": 3094244389412,
      "volume24h": 123263508914,
      "high24h": 51.47,
      "low24h": 48.38
    },
    {
      "id": "solana",
      "symbol": "SOL",
      "name": "Solana",
      "icon": "◎",
      "price": 3177.49,
      "priceUsd": 100.87269841269841,
      "change24h": -3.94816,
      "marketCap": 1801897401146,
      "volume24h": 184508677793,
      "high24h": 3315.89,
      "low24h": 3062.77
    },
    {
      "id": "dogecoin",
      "symbol": "DOGE",
      "name": "Dogecoin",
      "icon": "🐕",
      "price": 3.41,
      "priceUsd": 0.10825396825396826,
      "change24h": -0.12403,
      "marketCap": 575723596589,
      "volume24h": 62622414448,
      "high24h": 3.47,
      "low24h": 3.24
    },
    {
      "id": "cardano",
      "symbol": "ADA",
      "name": "Cardano",
      "icon": "₳",
      "price": 9.41,
      "priceUsd": 0.29873015873015873,
      "change24h": -0.93378,
      "marketCap": 346749835355,
      "volume24h": 22352909481,
      "high24h": 9.58,
      "low24h": 8.93
    },
    {
      "id": "chainlink",
      "symbol": "LINK",
      "name": "Chainlink",
      "icon": "⬡",
      "price": 306.7,
      "priceUsd": 9.736507936507936,
      "change24h": -0.87834,
      "marketCap": 217390083780,
      "volume24h": 20264248719,
      "high24h": 311.09,
      "low24h": 287.42
    },
    {
      "id": "avalanche-2",
      "symbol": "AVAX",
      "name": "Avalanche",
      "icon": "🔺",
      "price": 319.72,
      "priceUsd": 10.149841269841271,
      "change24h": -0.28209,
      "marketCap": 138164931979,
      "volume24h": 14014458669,
      "high24h": 322.95,
      "low24h": 301.92
    },
    {
      "id": "polkadot",
      "symbol": "DOT",
      "name": "Polkadot",
      "icon": "●",
      "price": 48.31,
      "priceUsd": 1.5336507936507937,
      "change24h": -1.10341,
      "marketCap": 80306302308,
      "volume24h": 6672428089,
      "high24h": 49.19,
      "low24h": 45.37
    }
  ]
}