{
  "updateTime": "2026-01-10T21:24:17.848Z",
  "updateTimeLocal": "2026/1/11 上午5:24:17",
  "currency": "TWD",
  "cryptos": [
    {
      "id": "bitcoin",
      "symbol": "BTC",
      "name": "Bitcoin",
      "icon": "₿",
      "price": 2858006,
      "priceUsd": 90730.3492063492,
      "change24h": 0.14581,
      "marketCap": 57078772425923,
      "volume24h": 466250141121,
      "high24h": 2867076,
      "low24h": 2853053
    },
    {
      "id": "ethereum",
      "symbol": "ETH",
      "name": "Ethereum",
      "icon": "Ξ",
      "price": 97504,
      "priceUsd": 3095.3650793650795,
      "change24h": 0.20371,
      "marketCap": 11764624499936,
      "volume24h": 226110788589,
      "high24h": 97931,
      "low24h": 97155
    },
    {
      "id": "ripple",
      "symbol": "XRP",
      "name": "XRP",
      "icon": "✕",
      "price": 65.96,
      "priceUsd": 2.093968253968254,
      "change24h": 0.3126,
      "marketCap": 4003791274029,
      "volume24h": 38888718572,
      "high24h": 66.53,
      "low24h": 65.73
    },
    {
      "id": "binancecoin",
      "symbol": "BNB",
      "name": "BNB",
      "icon": "🔶",
      "price": 28660,
      "priceUsd": 909.8412698412699,
      "change24h": 1.47992,
      "marketCap": 3947365869525,
      "volume24h": 40123383921,
      "high24h": 28897,
      "low24h": 28230
    },
    {
      "id": "solana",
      "symbol": "SOL",
      "name": "Solana",
      "icon": "◎",
      "price": 4291.33,
      "priceUsd": 136.2326984126984,
      "change24h": 0.02985,
      "marketCap": 2421273731137,
      "volume24h": 58317147656,
      "high24h": 4323.22,
      "low24h": 4284.71
    },
    {
      "id": "dogecoin",
      "symbol": "DOGE",
      "name": "Dogecoin",
      "icon": "🐕",
      "price": 4.41,
      "priceUsd": 0.14,
      "change24h": -0.22797,
      "marketCap": 673447126097,
      "volume24h": 14665276789,
      "high24h": 4.45,
      "low24h": 4.41
    },
    {
      "id": "cardano",
      "symbol": "ADA",
      "name": "Cardano",
      "icon": "₳",
      "price": 12.3,
      "priceUsd": 0.3904761904761905,
      "change24h": -0.4248,
      "marketCap": 451309727335,
      "volume24h": 7797315037,
      "high24h": 12.42,
      "low24h": 12.19
    },
    {
      "id": "chainlink",
      "symbol": "LINK",
      "name": "Chainlink",
      "icon": "⬡",
      "price": 416.28,
      "priceUsd": 13.215238095238094,
      "change24h": 0.433,
      "marketCap": 294898979537,
      "volume24h": 6176471565,
      "high24h": 417.97,
      "low24h": 413.03
    },
    {
      "id": "avalanche-2",
      "symbol": "AVAX",
      "name": "Avalanche",
      "icon": "🔺",
      "price": 436.27,
      "priceUsd": 13.849841269841269,
      "change24h": 0.27384,
      "marketCap": 187721012774,
      "volume24h": 4341690530,
      "high24h": 439.89,
      "low24h": 431.06
    },
    {
      "id": "polkadot",
      "symbol": "DOT",
      "name": "Polkadot",
      "icon": "●",
      "price": 66.64,
      "priceUsd": 2.1155555555555554,
      "change24h": 1.48706,
      "marketCap": 110217753524,
      "volume24h": 2286234135,
      "high24h": 67.2,
      "low24h": 65.45
    }
  ]
}