{
  "updateTime": "2026-01-31T16:37:58.869Z",
  "updateTimeLocal": "2026/2/1 上午12:37:58",
  "currency": "TWD",
  "cryptos": [
    {
      "id": "bitcoin",
      "symbol": "BTC",
      "name": "Bitcoin",
      "icon": "₿",
      "price": 2559084,
      "priceUsd": 81240.76190476191,
      "change24h": -2.3224,
      "marketCap": 51171512207358,
      "volume24h": 1855810794475,
      "high24h": 2663150,
      "low24h": 2555663
    },
    {
      "id": "ethereum",
      "symbol": "ETH",
      "name": "Ethereum",
      "icon": "Ξ",
      "price": 79563,
      "priceUsd": 2525.809523809524,
      "change24h": -7.76365,
      "marketCap": 9613749310736,
      "volume24h": 1135199066485,
      "high24h": 86843,
      "low24h": 79509
    },
    {
      "id": "binancecoin",
      "symbol": "BNB",
      "name": "BNB",
      "icon": "🔶",
      "price": 25277,
      "priceUsd": 802.4444444444445,
      "change24h": -5.7211,
      "marketCap": 3453279797873,
      "volume24h": 64900344186,
      "high24h": 27151,
      "low24h": 25248
    },
    {
      "id": "ripple",
      "symbol": "XRP",
      "name": "XRP",
      "icon": "✕",
      "price": 51.44,
      "priceUsd": 1.633015873015873,
      "change24h": -7.18128,
      "marketCap": 3134546566024,
      "volume24h": 133079544122,
      "high24h": 56.06,
      "low24h": 51.17
    },
    {
      "id": "solana",
      "symbol": "SOL",
      "name": "Solana",
      "icon": "◎",
      "price": 3419.31,
      "priceUsd": 108.5495238095238,
      "change24h": -7.30832,
      "marketCap": 1936717521218,
      "volume24h": 218500611189,
      "high24h": 3745.6,
      "low24h": 3416.13
    },
    {
      "id": "dogecoin",
      "symbol": "DOGE",
      "name": "Dogecoin",
      "icon": "🐕",
      "price": 3.37,
      "priceUsd": 0.10698412698412699,
      "change24h": -7.82326,
      "marketCap": 568941432855,
      "volume24h": 53043582687,
      "high24h": 3.73,
      "low24h": 3.36
    },
    {
      "id": "cardano",
      "symbol": "ADA",
      "name": "Cardano",
      "icon": "₳",
      "price": 9.37,
      "priceUsd": 0.2974603174603174,
      "change24h": -9.10893,
      "marketCap": 345715259565,
      "volume24h": 30567631915,
      "high24h": 10.44,
      "low24h": 9.34
    },
    {
      "id": "chainlink",
      "symbol": "LINK",
      "name": "Chainlink",
      "icon": "⬡",
      "price": 317.4,
      "priceUsd": 10.076190476190476,
      "change24h": -6.89894,
      "marketCap": 225600801177,
      "volume24h": 17470771193,
      "high24h": 345.58,
      "low24h": 314.68
    },
    {
      "id": "avalanche-2",
      "symbol": "AVAX",
      "name": "Avalanche",
      "icon": "🔺",
      "price": 321.6,
      "priceUsd": 10.20952380952381,
      "change24h": -6.66038,
      "marketCap": 138825355754,
      "volume24h": 14295684838,
      "high24h": 347.41,
      "low24h": 317.61
    },
    {
      "id": "polkadot",
      "symbol": "DOT",
      "name": "Polkadot",
      "icon": "●",
      "price": 49.63,
      "priceUsd": 1.5755555555555556,
      "change24h": -6.6845,
      "marketCap": 82442142960,
      "volume24h": 5836379821,
      "high24h": 54.19,
      "low24h": 48.73
    }
  ]
}