{
  "updateTime": "2026-01-31T21:29:10.919Z",
  "updateTimeLocal": "2026/2/1 上午5:29:10",
  "currency": "TWD",
  "cryptos": [
    {
      "id": "bitcoin",
      "symbol": "BTC",
      "name": "Bitcoin",
      "icon": "₿",
      "price": 2457015,
      "priceUsd": 78000.47619047618,
      "change24h": -7.67214,
      "marketCap": 48942563491786,
      "volume24h": 2350368065080,
      "high24h": 2661185,
      "low24h": 2435652
    },
    {
      "id": "ethereum",
      "symbol": "ETH",
      "name": "Ethereum",
      "icon": "Ξ",
      "price": 76005,
      "priceUsd": 2412.8571428571427,
      "change24h": -10.94289,
      "marketCap": 9123853342112,
      "volume24h": 1298343491819,
      "high24h": 85600,
      "low24h": 74403
    },
    {
      "id": "binancecoin",
      "symbol": "BNB",
      "name": "BNB",
      "icon": "🔶",
      "price": 24355,
      "priceUsd": 773.1746031746031,
      "change24h": -9.80542,
      "marketCap": 3307937696611,
      "volume24h": 81310942740,
      "high24h": 27151,
      "low24h": 24214
    },
    {
      "id": "ripple",
      "symbol": "XRP",
      "name": "XRP",
      "icon": "✕",
      "price": 50.49,
      "priceUsd": 1.602857142857143,
      "change24h": -8.3303,
      "marketCap": 3065914661649,
      "volume24h": 182983687977,
      "high24h": 55.25,
      "low24h": 49.34
    },
    {
      "id": "solana",
      "symbol": "SOL",
      "name": "Solana",
      "icon": "◎",
      "price": 3226.33,
      "priceUsd": 102.4231746031746,
      "change24h": -13.06456,
      "marketCap": 1819919272894,
      "volume24h": 301491287285,
      "high24h": 3745.6,
      "low24h": 3180.42
    },
    {
      "id": "dogecoin",
      "symbol": "DOGE",
      "name": "Dogecoin",
      "icon": "🐕",
      "price": 3.21,
      "priceUsd": 0.1019047619047619,
      "change24h": -12.53527,
      "marketCap": 539871122018,
      "volume24h": 81755493067,
      "high24h": 3.67,
      "low24h": 3.17
    },
    {
      "id": "cardano",
      "symbol": "ADA",
      "name": "Cardano",
      "icon": "₳",
      "price": 9.05,
      "priceUsd": 0.28730158730158734,
      "change24h": -11.96572,
      "marketCap": 331703367545,
      "volume24h": 41655528402,
      "high24h": 10.28,
      "low24h": 8.86
    },
    {
      "id": "chainlink",
      "symbol": "LINK",
      "name": "Chainlink",
      "icon": "⬡",
      "price": 306.3,
      "priceUsd": 9.723809523809525,
      "change24h": -10.06803,
      "marketCap": 216182407628,
      "volume24h": 27290510332,
      "high24h": 341.02,
      "low24h": 296.72
    },
    {
      "id": "avalanche-2",
      "symbol": "AVAX",
      "name": "Avalanche",
      "icon": "🔺",
      "price": 312.05,
      "priceUsd": 9.906349206349207,
      "change24h": -9.36569,
      "marketCap": 134525656539,
      "volume24h": 20701886211,
      "high24h": 344.53,
      "low24h": 302.86
    },
    {
      "id": "polkadot",
      "symbol": "DOT",
      "name": "Polkadot",
      "icon": "●",
      "price": 47.51,
      "priceUsd": 1.5082539682539682,
      "change24h": -11.17151,
      "marketCap": 78707221231,
      "volume24h": 7972914972,
      "high24h": 53.51,
      "low24h": 46.34
    }
  ]
}