{
  "updateTime": "2025-12-29T12:59:12.009Z",
  "updateTimeLocal": "2025/12/29 下午8:59:12",
  "currency": "TWD",
  "cryptos": [
    {
      "id": "bitcoin",
      "symbol": "BTC",
      "name": "Bitcoin",
      "icon": "₿",
      "price": 2734117,
      "priceUsd": 86797.36507936507,
      "change24h": -0.8089,
      "marketCap": 54627278742040,
      "volume24h": 1389259240416,
      "high24h": 2831880,
      "low24h": 2720673
    },
    {
      "id": "ethereum",
      "symbol": "ETH",
      "name": "Ethereum",
      "icon": "Ξ",
      "price": 91718,
      "priceUsd": 2911.6825396825398,
      "change24h": -0.54005,
      "marketCap": 11075798961267,
      "volume24h": 745896889319,
      "high24h": 95753,
      "low24h": 91270
    },
    {
      "id": "binancecoin",
      "symbol": "BNB",
      "name": "BNB",
      "icon": "🔶",
      "price": 26662,
      "priceUsd": 846.4126984126984,
      "change24h": -0.70979,
      "marketCap": 3672954344220,
      "volume24h": 52880214823,
      "high24h": 27319,
      "low24h": 26511
    },
    {
      "id": "ripple",
      "symbol": "XRP",
      "name": "XRP",
      "icon": "✕",
      "price": 58.45,
      "priceUsd": 1.8555555555555556,
      "change24h": -0.19522,
      "marketCap": 3541313958308,
      "volume24h": 60310382840,
      "high24h": 60.07,
      "low24h": 58.16
    },
    {
      "id": "solana",
      "symbol": "SOL",
      "name": "Solana",
      "icon": "◎",
      "price": 3871.62,
      "priceUsd": 122.90857142857142,
      "change24h": -0.82258,
      "marketCap": 2179014328578,
      "volume24h": 156212373924,
      "high24h": 4055.46,
      "low24h": 3864.74
    },
    {
      "id": "dogecoin",
      "symbol": "DOGE",
      "name": "Dogecoin",
      "icon": "🐕",
      "price": 3.88,
      "priceUsd": 0.12317460317460317,
      "change24h": -0.25619,
      "marketCap": 651520472712,
      "volume24h": 28184695380,
      "high24h": 4.01,
      "low24h": 3.85
    },
    {
      "id": "cardano",
      "symbol": "ADA",
      "name": "Cardano",
      "icon": "₳",
      "price": 11.44,
      "priceUsd": 0.36317460317460315,
      "change24h": -1.33771,
      "marketCap": 419534472663,
      "volume24h": 21116328740,
      "high24h": 12,
      "low24h": 11.37
    },
    {
      "id": "chainlink",
      "symbol": "LINK",
      "name": "Chainlink",
      "icon": "⬡",
      "price": 387.53,
      "priceUsd": 12.302539682539681,
      "change24h": -0.85301,
      "marketCap": 274426837784,
      "volume24h": 13636979875,
      "high24h": 407,
      "low24h": 384.85
    },
    {
      "id": "avalanche-2",
      "symbol": "AVAX",
      "name": "Avalanche",
      "icon": "🔺",
      "price": 394.33,
      "priceUsd": 12.518412698412698,
      "change24h": -0.62436,
      "marketCap": 169351897017,
      "volume24h": 10937535018,
      "high24h": 411.78,
      "low24h": 392.53
    },
    {
      "id": "polkadot",
      "symbol": "DOT",
      "name": "Polkadot",
      "icon": "●",
      "price": 57.53,
      "priceUsd": 1.8263492063492064,
      "change24h": -2.0085,
      "marketCap": 94956511887,
      "volume24h": 4453982645,
      "high24h": 59.6,
      "low24h": 57.13
    }
  ]
}