{
  "updateTime": "2026-01-26T06:49:17.928Z",
  "updateTimeLocal": "2026/1/26 下午2:49:17",
  "currency": "TWD",
  "cryptos": [
    {
      "id": "bitcoin",
      "symbol": "BTC",
      "name": "Bitcoin",
      "icon": "₿",
      "price": 2763325,
      "priceUsd": 87724.60317460318,
      "change24h": -0.74883,
      "marketCap": 55212747208306,
      "volume24h": 1598063331737,
      "high24h": 2787085,
      "low24h": 2703065
    },
    {
      "id": "ethereum",
      "symbol": "ETH",
      "name": "Ethereum",
      "icon": "Ξ",
      "price": 90781,
      "priceUsd": 2881.936507936508,
      "change24h": -1.61506,
      "marketCap": 10951768567379,
      "volume24h": 925915594227,
      "high24h": 92324,
      "low24h": 87483
    },
    {
      "id": "binancecoin",
      "symbol": "BNB",
      "name": "BNB",
      "icon": "🔶",
      "price": 27427,
      "priceUsd": 870.6984126984127,
      "change24h": -0.7945,
      "marketCap": 3739525440324,
      "volume24h": 46025123358,
      "high24h": 27671,
      "low24h": 26853
    },
    {
      "id": "ripple",
      "symbol": "XRP",
      "name": "XRP",
      "icon": "✕",
      "price": 59.14,
      "priceUsd": 1.8774603174603175,
      "change24h": -0.58891,
      "marketCap": 3596200853212,
      "volume24h": 100103785846,
      "high24h": 59.86,
      "low24h": 56.93
    },
    {
      "id": "solana",
      "symbol": "SOL",
      "name": "Solana",
      "icon": "◎",
      "price": 3849.31,
      "priceUsd": 122.20031746031746,
      "change24h": -3.05151,
      "marketCap": 2178722167320,
      "volume24h": 205005505966,
      "high24h": 3981.11,
      "low24h": 3695.73
    },
    {
      "id": "dogecoin",
      "symbol": "DOGE",
      "name": "Dogecoin",
      "icon": "🐕",
      "price": 3.82,
      "priceUsd": 0.12126984126984126,
      "change24h": -1.13966,
      "marketCap": 642462128090,
      "volume24h": 35464467523,
      "high24h": 3.87,
      "low24h": 3.7
    },
    {
      "id": "cardano",
      "symbol": "ADA",
      "name": "Cardano",
      "icon": "₳",
      "price": 10.94,
      "priceUsd": 0.3473015873015873,
      "change24h": -2.04372,
      "marketCap": 401596395704,
      "volume24h": 18264759863,
      "high24h": 11.27,
      "low24h": 10.47
    },
    {
      "id": "chainlink",
      "symbol": "LINK",
      "name": "Chainlink",
      "icon": "⬡",
      "price": 371.19,
      "priceUsd": 11.783809523809524,
      "change24h": -2.10948,
      "marketCap": 262537530175,
      "volume24h": 15564409629,
      "high24h": 379.72,
      "low24h": 357.39
    },
    {
      "id": "avalanche-2",
      "symbol": "AVAX",
      "name": "Avalanche",
      "icon": "🔺",
      "price": 365.91,
      "priceUsd": 11.616190476190477,
      "change24h": -2.30183,
      "marketCap": 157650094614,
      "volume24h": 10591975280,
      "high24h": 377.34,
      "low24h": 353.89
    },
    {
      "id": "polkadot",
      "symbol": "DOT",
      "name": "Polkadot",
      "icon": "●",
      "price": 58.19,
      "priceUsd": 1.8473015873015872,
      "change24h": -2.62459,
      "marketCap": 96424358704,
      "volume24h": 4296904862,
      "high24h": 60.08,
      "low24h": 56.26
    }
  ]
}