{
  "updateTime": "2025-12-21T12:52:03.609Z",
  "updateTimeLocal": "2025/12/21 下午8:52:03",
  "currency": "TWD",
  "cryptos": [
    {
      "id": "bitcoin",
      "symbol": "BTC",
      "name": "Bitcoin",
      "icon": "₿",
      "price": 2791668,
      "priceUsd": 88624.38095238095,
      "change24h": 0.41149,
      "marketCap": 55737032417489,
      "volume24h": 578298198088,
      "high24h": 2803564,
      "low24h": 2770399
    },
    {
      "id": "ethereum",
      "symbol": "ETH",
      "name": "Ethereum",
      "icon": "Ξ",
      "price": 94165,
      "priceUsd": 2989.3650793650795,
      "change24h": -0.0046,
      "marketCap": 11361624368042,
      "volume24h": 264664810579,
      "high24h": 94726,
      "low24h": 93390
    },
    {
      "id": "binancecoin",
      "symbol": "BNB",
      "name": "BNB",
      "icon": "🔶",
      "price": 27012,
      "priceUsd": 857.5238095238095,
      "change24h": 0.53685,
      "marketCap": 3719333205164,
      "volume24h": 21401474726,
      "high24h": 27073,
      "low24h": 26692
    },
    {
      "id": "ripple",
      "symbol": "XRP",
      "name": "XRP",
      "icon": "✕",
      "price": 60.82,
      "priceUsd": 1.9307936507936507,
      "change24h": -0.57393,
      "marketCap": 3684492707631,
      "volume24h": 72470090673,
      "high24h": 61.36,
      "low24h": 60.49
    },
    {
      "id": "solana",
      "symbol": "SOL",
      "name": "Solana",
      "icon": "◎",
      "price": 3952.88,
      "priceUsd": 125.48825396825397,
      "change24h": -0.59937,
      "marketCap": 2223253253535,
      "volume24h": 66865971072,
      "high24h": 3988.36,
      "low24h": 3930.68
    },
    {
      "id": "dogecoin",
      "symbol": "DOGE",
      "name": "Dogecoin",
      "icon": "🐕",
      "price": 4.14,
      "priceUsd": 0.13142857142857142,
      "change24h": -0.18007,
      "marketCap": 696205641282,
      "volume24h": 17306397245,
      "high24h": 4.19,
      "low24h": 4.12
    },
    {
      "id": "cardano",
      "symbol": "ADA",
      "name": "Cardano",
      "icon": "₳",
      "price": 11.6,
      "priceUsd": 0.3682539682539682,
      "change24h": -2.31439,
      "marketCap": 425352968335,
      "volume24h": 11636553694,
      "high24h": 11.94,
      "low24h": 11.56
    },
    {
      "id": "chainlink",
      "symbol": "LINK",
      "name": "Chainlink",
      "icon": "⬡",
      "price": 394.66,
      "priceUsd": 12.52888888888889,
      "change24h": -0.89368,
      "marketCap": 279926556755,
      "volume24h": 8833357973,
      "high24h": 399.59,
      "low24h": 390.7
    },
    {
      "id": "avalanche-2",
      "symbol": "AVAX",
      "name": "Avalanche",
      "icon": "🔺",
      "price": 385.39,
      "priceUsd": 12.234603174603174,
      "change24h": -0.37867,
      "marketCap": 165547133532,
      "volume24h": 5432911642,
      "high24h": 387.85,
      "low24h": 381.47
    },
    {
      "id": "polkadot",
      "symbol": "DOT",
      "name": "Polkadot",
      "icon": "●",
      "price": 57.22,
      "priceUsd": 1.8165079365079364,
      "change24h": -1.7964,
      "marketCap": 94323414228,
      "volume24h": 2914282629,
      "high24h": 58.29,
      "low24h": 56.81
    }
  ]
}