{
  "updateTime": "2025-12-07T15:23:20.168Z",
  "updateTimeLocal": "2025/12/7 下午11:23:20",
  "currency": "TWD",
  "cryptos": [
    {
      "id": "bitcoin",
      "symbol": "BTC",
      "name": "Bitcoin",
      "icon": "₿",
      "price": 2778956,
      "priceUsd": 88220.8253968254,
      "change24h": -0.87572,
      "marketCap": 55356095369555,
      "volume24h": 772907696727,
      "high24h": 2815176,
      "low24h": 2749902
    },
    {
      "id": "ethereum",
      "symbol": "ETH",
      "name": "Ethereum",
      "icon": "Ξ",
      "price": 92589,
      "priceUsd": 2939.3333333333335,
      "change24h": -2.49352,
      "marketCap": 11161399913182,
      "volume24h": 414967298927,
      "high24h": 95804,
      "low24h": 92045
    },
    {
      "id": "ripple",
      "symbol": "XRP",
      "name": "XRP",
      "icon": "✕",
      "price": 63.17,
      "priceUsd": 2.0053968253968253,
      "change24h": -0.38093,
      "marketCap": 3800969315059,
      "volume24h": 61589650938,
      "high24h": 64.79,
      "low24h": 62.59
    },
    {
      "id": "binancecoin",
      "symbol": "BNB",
      "name": "BNB",
      "icon": "🔶",
      "price": 27523,
      "priceUsd": 873.7460317460317,
      "change24h": -1.15599,
      "marketCap": 3799746523187,
      "volume24h": 30051559162,
      "high24h": 28098,
      "low24h": 27279
    },
    {
      "id": "solana",
      "symbol": "SOL",
      "name": "Solana",
      "icon": "◎",
      "price": 4040.06,
      "priceUsd": 128.25587301587302,
      "change24h": -2.50007,
      "marketCap": 2260113615396,
      "volume24h": 88766443067,
      "high24h": 4177.12,
      "low24h": 4013.19
    },
    {
      "id": "dogecoin",
      "symbol": "DOGE",
      "name": "Dogecoin",
      "icon": "🐕",
      "price": 4.27,
      "priceUsd": 0.13555555555555554,
      "change24h": -1.97084,
      "marketCap": 686704804420,
      "volume24h": 23372143538,
      "high24h": 4.4,
      "low24h": 4.23
    },
    {
      "id": "cardano",
      "symbol": "ADA",
      "name": "Cardano",
      "icon": "₳",
      "price": 12.86,
      "priceUsd": 0.40825396825396826,
      "change24h": -0.75982,
      "marketCap": 471728105139,
      "volume24h": 14454224335,
      "high24h": 13.15,
      "low24h": 12.75
    },
    {
      "id": "chainlink",
      "symbol": "LINK",
      "name": "Chainlink",
      "icon": "⬡",
      "price": 418.06,
      "priceUsd": 13.271746031746032,
      "change24h": -3.36358,
      "marketCap": 291747470749,
      "volume24h": 15432839080,
      "high24h": 439.86,
      "low24h": 414.43
    },
    {
      "id": "avalanche-2",
      "symbol": "AVAX",
      "name": "Avalanche",
      "icon": "🔺",
      "price": 410.36,
      "priceUsd": 13.027301587301588,
      "change24h": -0.93641,
      "marketCap": 176281475807,
      "volume24h": 9055631209,
      "high24h": 423.4,
      "low24h": 407.29
    },
    {
      "id": "polkadot",
      "symbol": "DOT",
      "name": "Polkadot",
      "icon": "●",
      "price": 64.9,
      "priceUsd": 2.0603174603174605,
      "change24h": -2.10831,
      "marketCap": 106014296675,
      "volume24h": 4536808694,
      "high24h": 67.64,
      "low24h": 64.29
    }
  ]
}