{
  "updateTime": "2025-12-19T13:38:12.761Z",
  "updateTimeLocal": "2025/12/19 下午9:38:12",
  "currency": "TWD",
  "cryptos": [
    {
      "id": "bitcoin",
      "symbol": "BTC",
      "name": "Bitcoin",
      "icon": "₿",
      "price": 2773229,
      "priceUsd": 88039.01587301587,
      "change24h": -0.23575,
      "marketCap": 55350894689125,
      "volume24h": 2051843080650,
      "high24h": 2811227,
      "low24h": 2669086
    },
    {
      "id": "ethereum",
      "symbol": "ETH",
      "name": "Ethereum",
      "icon": "Ξ",
      "price": 93319,
      "priceUsd": 2962.5079365079364,
      "change24h": 1.91406,
      "marketCap": 11257979178444,
      "volume24h": 1168300020358,
      "high24h": 94196,
      "low24h": 87789
    },
    {
      "id": "binancecoin",
      "symbol": "BNB",
      "name": "BNB",
      "icon": "🔶",
      "price": 26699,
      "priceUsd": 847.5873015873016,
      "change24h": 0.34504,
      "marketCap": 3676007623194,
      "volume24h": 204426600913,
      "high24h": 26810,
      "low24h": 25883
    },
    {
      "id": "ripple",
      "symbol": "XRP",
      "name": "XRP",
      "icon": "✕",
      "price": 59.12,
      "priceUsd": 1.8768253968253967,
      "change24h": -1.6292,
      "marketCap": 3580978233407,
      "volume24h": 157908344914,
      "high24h": 60.81,
      "low24h": 55.93
    },
    {
      "id": "solana",
      "symbol": "SOL",
      "name": "Solana",
      "icon": "◎",
      "price": 3975.06,
      "priceUsd": 126.19238095238094,
      "change24h": 0.62451,
      "marketCap": 2234000495164,
      "volume24h": 247974141871,
      "high24h": 4051.22,
      "low24h": 3711
    },
    {
      "id": "dogecoin",
      "symbol": "DOGE",
      "name": "Dogecoin",
      "icon": "🐕",
      "price": 4.05,
      "priceUsd": 0.12857142857142856,
      "change24h": 0.43482,
      "marketCap": 617096081002,
      "volume24h": 61698292179,
      "high24h": 4.11,
      "low24h": 3.8
    },
    {
      "id": "cardano",
      "symbol": "ADA",
      "name": "Cardano",
      "icon": "₳",
      "price": 11.56,
      "priceUsd": 0.366984126984127,
      "change24h": -1.16846,
      "marketCap": 423994468916,
      "volume24h": 24877655771,
      "high24h": 11.88,
      "low24h": 10.95
    },
    {
      "id": "chainlink",
      "symbol": "LINK",
      "name": "Chainlink",
      "icon": "⬡",
      "price": 392.29,
      "priceUsd": 12.453650793650795,
      "change24h": -0.29897,
      "marketCap": 273660836706,
      "volume24h": 25088173278,
      "high24h": 403.01,
      "low24h": 371.76
    },
    {
      "id": "avalanche-2",
      "symbol": "AVAX",
      "name": "Avalanche",
      "icon": "🔺",
      "price": 378.38,
      "priceUsd": 12.012063492063492,
      "change24h": -0.20007,
      "marketCap": 162379772873,
      "volume24h": 17840266270,
      "high24h": 386.77,
      "low24h": 355.73
    },
    {
      "id": "polkadot",
      "symbol": "DOT",
      "name": "Polkadot",
      "icon": "●",
      "price": 57.2,
      "priceUsd": 1.8158730158730159,
      "change24h": -1.20639,
      "marketCap": 94243873075,
      "volume24h": 7387569152,
      "high24h": 59.25,
      "low24h": 54.57
    }
  ]
}