{
  "updateTime": "2025-12-31T07:29:05.975Z",
  "updateTimeLocal": "2025/12/31 下午3:29:05",
  "currency": "TWD",
  "cryptos": [
    {
      "id": "bitcoin",
      "symbol": "BTC",
      "name": "Bitcoin",
      "icon": "₿",
      "price": 2777920,
      "priceUsd": 88187.93650793651,
      "change24h": 1.41603,
      "marketCap": 55430683533560,
      "volume24h": 1222287490212,
      "high24h": 2790624,
      "low24h": 2739133
    },
    {
      "id": "ethereum",
      "symbol": "ETH",
      "name": "Ethereum",
      "icon": "Ξ",
      "price": 93351,
      "priceUsd": 2963.5238095238096,
      "change24h": 0.99971,
      "marketCap": 11257140234942,
      "volume24h": 531466140907,
      "high24h": 93957,
      "low24h": 92304
    },
    {
      "id": "binancecoin",
      "symbol": "BNB",
      "name": "BNB",
      "icon": "🔶",
      "price": 27160,
      "priceUsd": 862.2222222222222,
      "change24h": 1.48514,
      "marketCap": 3739805446538,
      "volume24h": 38099999152,
      "high24h": 27211,
      "low24h": 26724
    },
    {
      "id": "ripple",
      "symbol": "XRP",
      "name": "XRP",
      "icon": "✕",
      "price": 58.7,
      "priceUsd": 1.8634920634920635,
      "change24h": 0.65933,
      "marketCap": 3561111387507,
      "volume24h": 56509430966,
      "high24h": 59.03,
      "low24h": 58.17
    },
    {
      "id": "solana",
      "symbol": "SOL",
      "name": "Solana",
      "icon": "◎",
      "price": 3948.05,
      "priceUsd": 125.33492063492064,
      "change24h": 1.70878,
      "marketCap": 2221741962535,
      "volume24h": 111503892286,
      "high24h": 3957,
      "low24h": 3863.15
    },
    {
      "id": "dogecoin",
      "symbol": "DOGE",
      "name": "Dogecoin",
      "icon": "🐕",
      "price": 3.86,
      "priceUsd": 0.12253968253968253,
      "change24h": -0.16127,
      "marketCap": 648886805960,
      "volume24h": 27023059480,
      "high24h": 3.91,
      "low24h": 3.83
    },
    {
      "id": "cardano",
      "symbol": "ADA",
      "name": "Cardano",
      "icon": "₳",
      "price": 11.03,
      "priceUsd": 0.3501587301587301,
      "change24h": 0.15096,
      "marketCap": 404665433317,
      "volume24h": 14398380476,
      "high24h": 11.15,
      "low24h": 10.9
    },
    {
      "id": "chainlink",
      "symbol": "LINK",
      "name": "Chainlink",
      "icon": "⬡",
      "price": 387.77,
      "priceUsd": 12.31015873015873,
      "change24h": 0.10138,
      "marketCap": 274614924245,
      "volume24h": 9976164470,
      "high24h": 392.65,
      "low24h": 385.66
    },
    {
      "id": "avalanche-2",
      "symbol": "AVAX",
      "name": "Avalanche",
      "icon": "🔺",
      "price": 393.21,
      "priceUsd": 12.482857142857142,
      "change24h": 0.93846,
      "marketCap": 168974761884,
      "volume24h": 7520282955,
      "high24h": 397.93,
      "low24h": 389.27
    },
    {
      "id": "polkadot",
      "symbol": "DOT",
      "name": "Polkadot",
      "icon": "●",
      "price": 56.83,
      "priceUsd": 1.804126984126984,
      "change24h": -0.0449,
      "marketCap": 93829358859,
      "volume24h": 3644761696,
      "high24h": 57.58,
      "low24h": 56.37
    }
  ]
}