{
  "updateTime": "2026-01-15T09:35:18.770Z",
  "updateTimeLocal": "2026/1/15 下午5:35:18",
  "currency": "TWD",
  "cryptos": [
    {
      "id": "bitcoin",
      "symbol": "BTC",
      "name": "Bitcoin",
      "icon": "₿",
      "price": 3053572,
      "priceUsd": 96938.79365079365,
      "change24h": 1.7204,
      "marketCap": 60958856656690,
      "volume24h": 2118389294833,
      "high24h": 3083616,
      "low24h": 2995049
    },
    {
      "id": "ethereum",
      "symbol": "ETH",
      "name": "Ethereum",
      "icon": "Ξ",
      "price": 105572,
      "priceUsd": 3351.4920634920636,
      "change24h": 0.32643,
      "marketCap": 12731560580151,
      "volume24h": 1065990824134,
      "high24h": 106886,
      "low24h": 103654
    },
    {
      "id": "binancecoin",
      "symbol": "BNB",
      "name": "BNB",
      "icon": "🔶",
      "price": 29687,
      "priceUsd": 942.4444444444445,
      "change24h": 0.26656,
      "marketCap": 4045683338994,
      "volume24h": 65077079257,
      "high24h": 29925,
      "low24h": 29347
    },
    {
      "id": "ripple",
      "symbol": "XRP",
      "name": "XRP",
      "icon": "✕",
      "price": 66.33,
      "priceUsd": 2.105714285714286,
      "change24h": -2.29347,
      "marketCap": 4025565941266,
      "volume24h": 127090353213,
      "high24h": 68.5,
      "low24h": 65.89
    },
    {
      "id": "solana",
      "symbol": "SOL",
      "name": "Solana",
      "icon": "◎",
      "price": 4576.76,
      "priceUsd": 145.29396825396827,
      "change24h": -0.37272,
      "marketCap": 2586864526816,
      "volume24h": 197131120067,
      "high24h": 4668.42,
      "low24h": 4531.18
    },
    {
      "id": "dogecoin",
      "symbol": "DOGE",
      "name": "Dogecoin",
      "icon": "🐕",
      "price": 4.54,
      "priceUsd": 0.14412698412698413,
      "change24h": -3.02451,
      "marketCap": 764646304632,
      "volume24h": 54859627050,
      "high24h": 4.74,
      "low24h": 4.51
    },
    {
      "id": "cardano",
      "symbol": "ADA",
      "name": "Cardano",
      "icon": "₳",
      "price": 12.7,
      "priceUsd": 0.40317460317460313,
      "change24h": -4.47315,
      "marketCap": 466979067375,
      "volume24h": 21524494529,
      "high24h": 13.33,
      "low24h": 12.64
    },
    {
      "id": "chainlink",
      "symbol": "LINK",
      "name": "Chainlink",
      "icon": "⬡",
      "price": 439.75,
      "priceUsd": 13.96031746031746,
      "change24h": -1.17052,
      "marketCap": 311284923005,
      "volume24h": 19762757673,
      "high24h": 453.44,
      "low24h": 434.63
    },
    {
      "id": "avalanche-2",
      "symbol": "AVAX",
      "name": "Avalanche",
      "icon": "🔺",
      "price": 454.22,
      "priceUsd": 14.41968253968254,
      "change24h": -2.17752,
      "marketCap": 195709461048,
      "volume24h": 15621953718,
      "high24h": 469.8,
      "low24h": 446.74
    },
    {
      "id": "polkadot",
      "symbol": "DOT",
      "name": "Polkadot",
      "icon": "●",
      "price": 69.1,
      "priceUsd": 2.1936507936507934,
      "change24h": -3.72321,
      "marketCap": 114367685295,
      "volume24h": 5897160768,
      "high24h": 72.28,
      "low24h": 68.4
    }
  ]
}