{
  "updateTime": "2026-01-27T15:36:53.220Z",
  "updateTimeLocal": "2026/1/27 下午11:36:53",
  "currency": "TWD",
  "cryptos": [
    {
      "id": "bitcoin",
      "symbol": "BTC",
      "name": "Bitcoin",
      "icon": "₿",
      "price": 2751643,
      "priceUsd": 87353.74603174604,
      "change24h": -0.68884,
      "marketCap": 54977800052855,
      "volume24h": 1194502940084,
      "high24h": 2793067,
      "low24h": 2740725
    },
    {
      "id": "ethereum",
      "symbol": "ETH",
      "name": "Ethereum",
      "icon": "Ξ",
      "price": 91546,
      "priceUsd": 2906.222222222222,
      "change24h": 0.21319,
      "marketCap": 11048136332018,
      "volume24h": 761239175079,
      "high24h": 92766,
      "low24h": 90798
    },
    {
      "id": "binancecoin",
      "symbol": "BNB",
      "name": "BNB",
      "icon": "🔶",
      "price": 27707,
      "priceUsd": 879.5873015873016,
      "change24h": 0.95086,
      "marketCap": 3778406682679,
      "volume24h": 39254525551,
      "high24h": 27892,
      "low24h": 27335
    },
    {
      "id": "ripple",
      "symbol": "XRP",
      "name": "XRP",
      "icon": "✕",
      "price": 59.04,
      "priceUsd": 1.8742857142857143,
      "change24h": -2.52705,
      "marketCap": 3593260252554,
      "volume24h": 66916968564,
      "high24h": 60.61,
      "low24h": 58.92
    },
    {
      "id": "solana",
      "symbol": "SOL",
      "name": "Solana",
      "icon": "◎",
      "price": 3883.7,
      "priceUsd": 123.29206349206349,
      "change24h": -0.29726,
      "marketCap": 2198483899262,
      "volume24h": 108886378933,
      "high24h": 3928.66,
      "low24h": 3869.6
    },
    {
      "id": "dogecoin",
      "symbol": "DOGE",
      "name": "Dogecoin",
      "icon": "🐕",
      "price": 3.83,
      "priceUsd": 0.12158730158730159,
      "change24h": -0.86131,
      "marketCap": 644692621609,
      "volume24h": 25134344574,
      "high24h": 3.87,
      "low24h": 3.82
    },
    {
      "id": "cardano",
      "symbol": "ADA",
      "name": "Cardano",
      "icon": "₳",
      "price": 10.96,
      "priceUsd": 0.347936507936508,
      "change24h": -1.23844,
      "marketCap": 403101706586,
      "volume24h": 10984274448,
      "high24h": 11.15,
      "low24h": 10.93
    },
    {
      "id": "chainlink",
      "symbol": "LINK",
      "name": "Chainlink",
      "icon": "⬡",
      "price": 373.53,
      "priceUsd": 11.858095238095236,
      "change24h": -1.02595,
      "marketCap": 264543294483,
      "volume24h": 7771154470,
      "high24h": 378.63,
      "low24h": 372.13
    },
    {
      "id": "avalanche-2",
      "symbol": "AVAX",
      "name": "Avalanche",
      "icon": "🔺",
      "price": 364.5,
      "priceUsd": 11.571428571428571,
      "change24h": -2.22907,
      "marketCap": 157218168142,
      "volume24h": 7690078859,
      "high24h": 372.81,
      "low24h": 364.5
    },
    {
      "id": "polkadot",
      "symbol": "DOT",
      "name": "Polkadot",
      "icon": "●",
      "price": 57.51,
      "priceUsd": 1.8257142857142856,
      "change24h": -2.61584,
      "marketCap": 95439293210,
      "volume24h": 3007890051,
      "high24h": 59.21,
      "low24h": 57.47
    }
  ]
}