{
  "updateTime": "2025-12-05T18:36:03.180Z",
  "updateTimeLocal": "2025/12/6 上午2:36:03",
  "currency": "TWD",
  "cryptos": [
    {
      "id": "bitcoin",
      "symbol": "BTC",
      "name": "Bitcoin",
      "icon": "₿",
      "price": 2793972,
      "priceUsd": 88697.52380952382,
      "change24h": -3.70192,
      "marketCap": 55825988085273,
      "volume24h": 1592545138241,
      "high24h": 2906349,
      "low24h": 2765974
    },
    {
      "id": "ethereum",
      "symbol": "ETH",
      "name": "Ethereum",
      "icon": "Ξ",
      "price": 94737,
      "priceUsd": 3007.5238095238096,
      "change24h": -4.36339,
      "marketCap": 11437133435247,
      "volume24h": 906523756083,
      "high24h": 99935,
      "low24h": 94116
    },
    {
      "id": "ripple",
      "symbol": "XRP",
      "name": "XRP",
      "icon": "✕",
      "price": 63.51,
      "priceUsd": 2.0161904761904763,
      "change24h": -4.50486,
      "marketCap": 3831467032901,
      "volume24h": 109612218032,
      "high24h": 66.51,
      "low24h": 63.34
    },
    {
      "id": "binancecoin",
      "symbol": "BNB",
      "name": "BNB",
      "icon": "🔶",
      "price": 27601,
      "priceUsd": 876.2222222222222,
      "change24h": -2.68676,
      "marketCap": 3798254895583,
      "volume24h": 51936451367,
      "high24h": 28419,
      "low24h": 27317
    },
    {
      "id": "solana",
      "symbol": "SOL",
      "name": "Solana",
      "icon": "◎",
      "price": 4132.68,
      "priceUsd": 131.19619047619048,
      "change24h": -7.19948,
      "marketCap": 2313814748171,
      "volume24h": 163283705198,
      "high24h": 4453.29,
      "low24h": 4118.02
    },
    {
      "id": "dogecoin",
      "symbol": "DOGE",
      "name": "Dogecoin",
      "icon": "🐕",
      "price": 4.33,
      "priceUsd": 0.13746031746031745,
      "change24h": -7.63194,
      "marketCap": 698021110139,
      "volume24h": 39388691994,
      "high24h": 4.69,
      "low24h": 4.32
    },
    {
      "id": "cardano",
      "symbol": "ADA",
      "name": "Cardano",
      "icon": "₳",
      "price": 12.94,
      "priceUsd": 0.41079365079365077,
      "change24h": -7.51607,
      "marketCap": 473997448093,
      "volume24h": 22249759385,
      "high24h": 13.99,
      "low24h": 12.87
    },
    {
      "id": "chainlink",
      "symbol": "LINK",
      "name": "Chainlink",
      "icon": "⬡",
      "price": 424.49,
      "priceUsd": 13.475873015873017,
      "change24h": -5.72731,
      "marketCap": 295762355892,
      "volume24h": 22118433437,
      "high24h": 450.52,
      "low24h": 419.74
    },
    {
      "id": "avalanche-2",
      "symbol": "AVAX",
      "name": "Avalanche",
      "icon": "🔺",
      "price": 418.9,
      "priceUsd": 13.298412698412697,
      "change24h": -8.14763,
      "marketCap": 179723773633,
      "volume24h": 13405359666,
      "high24h": 456.06,
      "low24h": 417.1
    },
    {
      "id": "polkadot",
      "symbol": "DOT",
      "name": "Polkadot",
      "icon": "●",
      "price": 66.07,
      "priceUsd": 2.097460317460317,
      "change24h": -8.91781,
      "marketCap": 108309747717,
      "volume24h": 5531077147,
      "high24h": 72.54,
      "low24h": 65.96
    }
  ]
}