{
  "updateTime": "2026-02-05T23:30:42.887Z",
  "updateTimeLocal": "2026/2/6 上午7:30:42",
  "currency": "TWD",
  "cryptos": [
    {
      "id": "bitcoin",
      "symbol": "BTC",
      "name": "Bitcoin",
      "icon": "₿",
      "price": 2034402,
      "priceUsd": 64584.19047619047,
      "change24h": -12.08606,
      "marketCap": 40608136154932,
      "volume24h": 4473410443315,
      "high24h": 2321929,
      "low24h": 1979750
    },
    {
      "id": "ethereum",
      "symbol": "ETH",
      "name": "Ethereum",
      "icon": "Ξ",
      "price": 59460,
      "priceUsd": 1887.6190476190477,
      "change24h": -12.52534,
      "marketCap": 7155496286037,
      "volume24h": 1960340469778,
      "high24h": 68406,
      "low24h": 57943
    },
    {
      "id": "binancecoin",
      "symbol": "BNB",
      "name": "BNB",
      "icon": "🔶",
      "price": 19603.12,
      "priceUsd": 622.3212698412698,
      "change24h": -11.3132,
      "marketCap": 2670325644955,
      "volume24h": 133579883382,
      "high24h": 22178,
      "low24h": 19125.35
    },
    {
      "id": "ripple",
      "symbol": "XRP",
      "name": "XRP",
      "icon": "✕",
      "price": 39.34,
      "priceUsd": 1.248888888888889,
      "change24h": -18.00316,
      "marketCap": 2396941049603,
      "volume24h": 379922595904,
      "high24h": 48.1,
      "low24h": 36.58
    },
    {
      "id": "solana",
      "symbol": "SOL",
      "name": "Solana",
      "icon": "◎",
      "price": 2524.8,
      "priceUsd": 80.15238095238095,
      "change24h": -12.67186,
      "marketCap": 1432561465745,
      "volume24h": 305996935087,
      "high24h": 2942.79,
      "low24h": 2476.18
    },
    {
      "id": "dogecoin",
      "symbol": "DOGE",
      "name": "Dogecoin",
      "icon": "🐕",
      "price": 2.85,
      "priceUsd": 0.09047619047619047,
      "change24h": -13.17233,
      "marketCap": 480960922898,
      "volume24h": 107338639086,
      "high24h": 3.3,
      "low24h": 2.78
    },
    {
      "id": "cardano",
      "symbol": "ADA",
      "name": "Cardano",
      "icon": "₳",
      "price": 7.94,
      "priceUsd": 0.2520634920634921,
      "change24h": -12.20733,
      "marketCap": 292482392153,
      "volume24h": 42383656018,
      "high24h": 9.12,
      "low24h": 7.78
    },
    {
      "id": "chainlink",
      "symbol": "LINK",
      "name": "Chainlink",
      "icon": "⬡",
      "price": 255.94,
      "priceUsd": 8.125079365079365,
      "change24h": -12.50969,
      "marketCap": 181340777788,
      "volume24h": 34973942320,
      "high24h": 294.28,
      "low24h": 250.06
    },
    {
      "id": "avalanche-2",
      "symbol": "AVAX",
      "name": "Avalanche",
      "icon": "🔺",
      "price": 267.44,
      "priceUsd": 8.490158730158731,
      "change24h": -12.86903,
      "marketCap": 115451705955,
      "volume24h": 25755182224,
      "high24h": 309.92,
      "low24h": 262.87
    },
    {
      "id": "polkadot",
      "symbol": "DOT",
      "name": "Polkadot",
      "icon": "●",
      "price": 40.22,
      "priceUsd": 1.2768253968253969,
      "change24h": -13.03558,
      "marketCap": 66869541100,
      "volume24h": 9341413917,
      "high24h": 46.54,
      "low24h": 39.53
    }
  ]
}