{
  "updateTime": "2026-01-19T14:35:18.432Z",
  "updateTimeLocal": "2026/1/19 下午10:35:18",
  "currency": "TWD",
  "cryptos": [
    {
      "id": "bitcoin",
      "symbol": "BTC",
      "name": "Bitcoin",
      "icon": "₿",
      "price": 2929405,
      "priceUsd": 92996.98412698413,
      "change24h": -2.68816,
      "marketCap": 58538119340491,
      "volume24h": 1332918463485,
      "high24h": 3018826,
      "low24h": 2911020
    },
    {
      "id": "ethereum",
      "symbol": "ETH",
      "name": "Ethereum",
      "icon": "Ξ",
      "price": 101272,
      "priceUsd": 3214.9841269841268,
      "change24h": -4.0602,
      "marketCap": 12226248391391,
      "volume24h": 932471258721,
      "high24h": 106388,
      "low24h": 100686
    },
    {
      "id": "binancecoin",
      "symbol": "BNB",
      "name": "BNB",
      "icon": "🔶",
      "price": 29186,
      "priceUsd": 926.5396825396825,
      "change24h": -2.58575,
      "marketCap": 3978735296351,
      "volume24h": 72257584631,
      "high24h": 30124,
      "low24h": 28823
    },
    {
      "id": "ripple",
      "symbol": "XRP",
      "name": "XRP",
      "icon": "✕",
      "price": 62.41,
      "priceUsd": 1.981269841269841,
      "change24h": -4.12103,
      "marketCap": 3792539517280,
      "volume24h": 120941056515,
      "high24h": 65.24,
      "low24h": 61.03
    },
    {
      "id": "solana",
      "symbol": "SOL",
      "name": "Solana",
      "icon": "◎",
      "price": 4213.35,
      "priceUsd": 133.75714285714287,
      "change24h": -6.45639,
      "marketCap": 2382745090478,
      "volume24h": 179743600696,
      "high24h": 4519.43,
      "low24h": 4193.29
    },
    {
      "id": "dogecoin",
      "symbol": "DOGE",
      "name": "Dogecoin",
      "icon": "🐕",
      "price": 4.06,
      "priceUsd": 0.1288888888888889,
      "change24h": -6.67328,
      "marketCap": 683750725600,
      "volume24h": 58806697877,
      "high24h": 4.36,
      "low24h": 3.98
    },
    {
      "id": "cardano",
      "symbol": "ADA",
      "name": "Cardano",
      "icon": "₳",
      "price": 11.66,
      "priceUsd": 0.3701587301587302,
      "change24h": -6.37824,
      "marketCap": 428436742842,
      "volume24h": 31598547703,
      "high24h": 12.53,
      "low24h": 11.36
    },
    {
      "id": "chainlink",
      "symbol": "LINK",
      "name": "Chainlink",
      "icon": "⬡",
      "price": 404.92,
      "priceUsd": 12.854603174603175,
      "change24h": -7.21382,
      "marketCap": 286672777906,
      "volume24h": 20846068792,
      "high24h": 438.22,
      "low24h": 401.78
    },
    {
      "id": "avalanche-2",
      "symbol": "AVAX",
      "name": "Avalanche",
      "icon": "🔺",
      "price": 401.73,
      "priceUsd": 12.753333333333334,
      "change24h": -6.55587,
      "marketCap": 173129766424,
      "volume24h": 14356593200,
      "high24h": 434.41,
      "low24h": 395.64
    },
    {
      "id": "polkadot",
      "symbol": "DOT",
      "name": "Polkadot",
      "icon": "●",
      "price": 62.61,
      "priceUsd": 1.9876190476190476,
      "change24h": -8.06593,
      "marketCap": 103728499713,
      "volume24h": 7769193967,
      "high24h": 69.27,
      "low24h": 61.21
    }
  ]
}