{
  "updateTime": "2025-12-11T15:33:06.359Z",
  "updateTimeLocal": "2025/12/11 下午11:33:06",
  "currency": "TWD",
  "cryptos": [
    {
      "id": "bitcoin",
      "symbol": "BTC",
      "name": "Bitcoin",
      "icon": "₿",
      "price": 2811861,
      "priceUsd": 89265.42857142857,
      "change24h": -1.96596,
      "marketCap": 56150210618465,
      "volume24h": 1792345754134,
      "high24h": 2926555,
      "low24h": 2790788
    },
    {
      "id": "ethereum",
      "symbol": "ETH",
      "name": "Ethereum",
      "icon": "Ξ",
      "price": 99270,
      "priceUsd": 3151.4285714285716,
      "change24h": -4.25741,
      "marketCap": 11997105658891,
      "volume24h": 1142131826459,
      "high24h": 106678,
      "low24h": 98607
    },
    {
      "id": "ripple",
      "symbol": "XRP",
      "name": "XRP",
      "icon": "✕",
      "price": 62.45,
      "priceUsd": 1.9825396825396826,
      "change24h": -3.28406,
      "marketCap": 3767612155810,
      "volume24h": 127822911796,
      "high24h": 65.14,
      "low24h": 62.06
    },
    {
      "id": "binancecoin",
      "symbol": "BNB",
      "name": "BNB",
      "icon": "🔶",
      "price": 27025,
      "priceUsd": 857.936507936508,
      "change24h": -2.71796,
      "marketCap": 3722026917554,
      "volume24h": 61002809299,
      "high24h": 28283,
      "low24h": 26885
    },
    {
      "id": "solana",
      "symbol": "SOL",
      "name": "Solana",
      "icon": "◎",
      "price": 4117.95,
      "priceUsd": 130.72857142857143,
      "change24h": -3.60583,
      "marketCap": 2317398733209,
      "volume24h": 230423277167,
      "high24h": 4400.41,
      "low24h": 4042.62
    },
    {
      "id": "dogecoin",
      "symbol": "DOGE",
      "name": "Dogecoin",
      "icon": "🐕",
      "price": 4.29,
      "priceUsd": 0.1361904761904762,
      "change24h": -5.3869,
      "marketCap": 653131237219,
      "volume24h": 54397163470,
      "high24h": 4.64,
      "low24h": 4.28
    },
    {
      "id": "cardano",
      "symbol": "ADA",
      "name": "Cardano",
      "icon": "₳",
      "price": 13.06,
      "priceUsd": 0.41460317460317464,
      "change24h": -9.59473,
      "marketCap": 478545829038,
      "volume24h": 38888844552,
      "high24h": 14.63,
      "low24h": 12.9
    },
    {
      "id": "chainlink",
      "symbol": "LINK",
      "name": "Chainlink",
      "icon": "⬡",
      "price": 425.63,
      "priceUsd": 13.512063492063492,
      "change24h": -2.98326,
      "marketCap": 296755880011,
      "volume24h": 27082494072,
      "high24h": 458.84,
      "low24h": 420.08
    },
    {
      "id": "avalanche-2",
      "symbol": "AVAX",
      "name": "Avalanche",
      "icon": "🔺",
      "price": 409.81,
      "priceUsd": 13.009841269841269,
      "change24h": -7.80732,
      "marketCap": 176307473672,
      "volume24h": 16794910892,
      "high24h": 456.11,
      "low24h": 408.57
    },
    {
      "id": "polkadot",
      "symbol": "DOT",
      "name": "Polkadot",
      "icon": "●",
      "price": 63.58,
      "priceUsd": 2.0184126984126984,
      "change24h": -7.87607,
      "marketCap": 104678756470,
      "volume24h": 8007265430,
      "high24h": 71.45,
      "low24h": 63.33
    }
  ]
}