{
  "updateTime": "2025-12-12T07:28:47.385Z",
  "updateTimeLocal": "2025/12/12 下午3:28:47",
  "currency": "TWD",
  "cryptos": [
    {
      "id": "bitcoin",
      "symbol": "BTC",
      "name": "Bitcoin",
      "icon": "₿",
      "price": 2883941,
      "priceUsd": 91553.68253968254,
      "change24h": 2.29087,
      "marketCap": 57588279087342,
      "volume24h": 1472969199725,
      "high24h": 2918010,
      "low24h": 2786884
    },
    {
      "id": "ethereum",
      "symbol": "ETH",
      "name": "Ethereum",
      "icon": "Ξ",
      "price": 101525,
      "priceUsd": 3223.0158730158732,
      "change24h": 1.55413,
      "marketCap": 12250610547178,
      "volume24h": 753795332018,
      "high24h": 101993,
      "low24h": 98486
    },
    {
      "id": "ripple",
      "symbol": "XRP",
      "name": "XRP",
      "icon": "✕",
      "price": 63.65,
      "priceUsd": 2.0206349206349206,
      "change24h": 1.2697,
      "marketCap": 3839682463068,
      "volume24h": 90310567453,
      "high24h": 64.09,
      "low24h": 61.93
    },
    {
      "id": "binancecoin",
      "symbol": "BNB",
      "name": "BNB",
      "icon": "🔶",
      "price": 27764,
      "priceUsd": 881.3968253968254,
      "change24h": 2.31139,
      "marketCap": 3825402094112,
      "volume24h": 43547497043,
      "high24h": 27975,
      "low24h": 26872
    },
    {
      "id": "solana",
      "symbol": "SOL",
      "name": "Solana",
      "icon": "◎",
      "price": 4337.03,
      "priceUsd": 137.68349206349205,
      "change24h": 5.84544,
      "marketCap": 2436372026122,
      "volume24h": 178870396376,
      "high24h": 4361.12,
      "low24h": 4064.15
    },
    {
      "id": "dogecoin",
      "symbol": "DOGE",
      "name": "Dogecoin",
      "icon": "🐕",
      "price": 4.39,
      "priceUsd": 0.13936507936507936,
      "change24h": 1.6575,
      "marketCap": 668353755318,
      "volume24h": 34977715081,
      "high24h": 4.44,
      "low24h": 4.26
    },
    {
      "id": "cardano",
      "symbol": "ADA",
      "name": "Cardano",
      "icon": "₳",
      "price": 13.31,
      "priceUsd": 0.42253968253968255,
      "change24h": -0.15367,
      "marketCap": 487823281452,
      "volume24h": 33760385737,
      "high24h": 13.37,
      "low24h": 12.83
    },
    {
      "id": "chainlink",
      "symbol": "LINK",
      "name": "Chainlink",
      "icon": "⬡",
      "price": 439.55,
      "priceUsd": 13.953968253968254,
      "change24h": 3.69471,
      "marketCap": 306253928043,
      "volume24h": 19014747432,
      "high24h": 442.61,
      "low24h": 419.05
    },
    {
      "id": "avalanche-2",
      "symbol": "AVAX",
      "name": "Avalanche",
      "icon": "🔺",
      "price": 429.69,
      "priceUsd": 13.640952380952381,
      "change24h": 2.44446,
      "marketCap": 184545012140,
      "volume24h": 13431336165,
      "high24h": 429.79,
      "low24h": 402.78
    },
    {
      "id": "polkadot",
      "symbol": "DOT",
      "name": "Polkadot",
      "icon": "●",
      "price": 64.42,
      "priceUsd": 2.0450793650793653,
      "change24h": -0.38198,
      "marketCap": 105928319654,
      "volume24h": 7039111239,
      "high24h": 65.26,
      "low24h": 62.82
    }
  ]
}