{
  "updateTime": "2026-02-04T11:38:37.314Z",
  "updateTimeLocal": "2026/2/4 下午7:38:37",
  "currency": "TWD",
  "cryptos": [
    {
      "id": "bitcoin",
      "symbol": "BTC",
      "name": "Bitcoin",
      "icon": "₿",
      "price": 2402120,
      "priceUsd": 76257.77777777778,
      "change24h": -2.71002,
      "marketCap": 48004972644907,
      "volume24h": 2402306336509,
      "high24h": 2473667,
      "low24h": 2310958
    },
    {
      "id": "ethereum",
      "symbol": "ETH",
      "name": "Ethereum",
      "icon": "Ξ",
      "price": 71225,
      "priceUsd": 2261.1111111111113,
      "change24h": -0.93866,
      "marketCap": 8596824893821,
      "volume24h": 1533313950812,
      "high24h": 73446,
      "low24h": 66916
    },
    {
      "id": "binancecoin",
      "symbol": "BNB",
      "name": "BNB",
      "icon": "🔶",
      "price": 23722,
      "priceUsd": 753.0793650793651,
      "change24h": -2.30815,
      "marketCap": 3234046227072,
      "volume24h": 63799262333,
      "high24h": 24506,
      "low24h": 23288
    },
    {
      "id": "ripple",
      "symbol": "XRP",
      "name": "XRP",
      "icon": "✕",
      "price": 50.22,
      "priceUsd": 1.5942857142857143,
      "change24h": -0.82567,
      "marketCap": 3055366275658,
      "volume24h": 133074809702,
      "high24h": 51.3,
      "low24h": 48.38
    },
    {
      "id": "solana",
      "symbol": "SOL",
      "name": "Solana",
      "icon": "◎",
      "price": 3039.91,
      "priceUsd": 96.50507936507935,
      "change24h": -6.60327,
      "marketCap": 1720566822720,
      "volume24h": 220054363541,
      "high24h": 3262.82,
      "low24h": 3012.01
    },
    {
      "id": "dogecoin",
      "symbol": "DOGE",
      "name": "Dogecoin",
      "icon": "🐕",
      "price": 3.38,
      "priceUsd": 0.1073015873015873,
      "change24h": 0.34265,
      "marketCap": 570322881529,
      "volume24h": 63877266457,
      "high24h": 3.47,
      "low24h": 3.24
    },
    {
      "id": "cardano",
      "symbol": "ADA",
      "name": "Cardano",
      "icon": "₳",
      "price": 9.38,
      "priceUsd": 0.2977777777777778,
      "change24h": 0.01333,
      "marketCap": 344840257523,
      "volume24h": 25068481369,
      "high24h": 9.58,
      "low24h": 8.93
    },
    {
      "id": "chainlink",
      "symbol": "LINK",
      "name": "Chainlink",
      "icon": "⬡",
      "price": 301.92,
      "priceUsd": 9.584761904761905,
      "change24h": -0.29771,
      "marketCap": 213673490019,
      "volume24h": 20358993864,
      "high24h": 310.85,
      "low24h": 287.42
    },
    {
      "id": "avalanche-2",
      "symbol": "AVAX",
      "name": "Avalanche",
      "icon": "🔺",
      "price": 315.77,
      "priceUsd": 10.024444444444445,
      "change24h": -0.7273,
      "marketCap": 136249445777,
      "volume24h": 14929560587,
      "high24h": 322.95,
      "low24h": 301.92
    },
    {
      "id": "polkadot",
      "symbol": "DOT",
      "name": "Polkadot",
      "icon": "●",
      "price": 47.31,
      "priceUsd": 1.501904761904762,
      "change24h": -1.30228,
      "marketCap": 78572546606,
      "volume24h": 6893156816,
      "high24h": 49.19,
      "low24h": 45.37
    }
  ]
}