{
  "updateTime": "2025-12-15T19:25:53.164Z",
  "updateTimeLocal": "2025/12/16 上午3:25:53",
  "currency": "TWD",
  "cryptos": [
    {
      "id": "bitcoin",
      "symbol": "BTC",
      "name": "Bitcoin",
      "icon": "₿",
      "price": 2705223,
      "priceUsd": 85880.09523809524,
      "change24h": -2.52444,
      "marketCap": 53922808222763,
      "volume24h": 1439101085030,
      "high24h": 2818065,
      "low24h": 2676941
    },
    {
      "id": "ethereum",
      "symbol": "ETH",
      "name": "Ethereum",
      "icon": "Ξ",
      "price": 92510,
      "priceUsd": 2936.8253968253966,
      "change24h": -4.56152,
      "marketCap": 11146272617412,
      "volume24h": 907760204794,
      "high24h": 99386,
      "low24h": 91258
    },
    {
      "id": "binancecoin",
      "symbol": "BNB",
      "name": "BNB",
      "icon": "🔶",
      "price": 26741,
      "priceUsd": 848.9206349206349,
      "change24h": -3.33074,
      "marketCap": 3675185338913,
      "volume24h": 53110640571,
      "high24h": 27982,
      "low24h": 26447
    },
    {
      "id": "ripple",
      "symbol": "XRP",
      "name": "XRP",
      "icon": "✕",
      "price": 59.57,
      "priceUsd": 1.8911111111111112,
      "change24h": -4.29485,
      "marketCap": 3595611133431,
      "volume24h": 99745764923,
      "high24h": 62.86,
      "low24h": 58.88
    },
    {
      "id": "solana",
      "symbol": "SOL",
      "name": "Solana",
      "icon": "◎",
      "price": 3928.7,
      "priceUsd": 124.72063492063492,
      "change24h": -3.64721,
      "marketCap": 2200741087837,
      "volume24h": 168671415989,
      "high24h": 4205.93,
      "low24h": 3892.81
    },
    {
      "id": "dogecoin",
      "symbol": "DOGE",
      "name": "Dogecoin",
      "icon": "🐕",
      "price": 4.04,
      "priceUsd": 0.12825396825396826,
      "change24h": -3.97315,
      "marketCap": 676448946440,
      "volume24h": 42495144229,
      "high24h": 4.32,
      "low24h": 3.99
    },
    {
      "id": "cardano",
      "symbol": "ADA",
      "name": "Cardano",
      "icon": "₳",
      "price": 12.1,
      "priceUsd": 0.3841269841269841,
      "change24h": -2.83273,
      "marketCap": 442055533981,
      "volume24h": 21619115726,
      "high24h": 12.71,
      "low24h": 11.89
    },
    {
      "id": "chainlink",
      "symbol": "LINK",
      "name": "Chainlink",
      "icon": "⬡",
      "price": 401.01,
      "priceUsd": 12.73047619047619,
      "change24h": -4.40877,
      "marketCap": 278870844891,
      "volume24h": 20746625907,
      "high24h": 429.15,
      "low24h": 393.4
    },
    {
      "id": "avalanche-2",
      "symbol": "AVAX",
      "name": "Avalanche",
      "icon": "🔺",
      "price": 389.28,
      "priceUsd": 12.358095238095236,
      "change24h": -4.25855,
      "marketCap": 166880107904,
      "volume24h": 13584855908,
      "high24h": 416.56,
      "low24h": 384.68
    },
    {
      "id": "polkadot",
      "symbol": "DOT",
      "name": "Polkadot",
      "icon": "●",
      "price": 58.94,
      "priceUsd": 1.871111111111111,
      "change24h": -4.19374,
      "marketCap": 96646522263,
      "volume24h": 6994182742,
      "high24h": 62.81,
      "low24h": 57.78
    }
  ]
}