{
  "updateTime": "2025-12-18T05:29:54.177Z",
  "updateTimeLocal": "2025/12/18 下午1:29:54",
  "currency": "TWD",
  "cryptos": [
    {
      "id": "bitcoin",
      "symbol": "BTC",
      "name": "Bitcoin",
      "icon": "₿",
      "price": 2728002,
      "priceUsd": 86603.23809523809,
      "change24h": -0.05111,
      "marketCap": 54452158244713,
      "volume24h": 1567387478505,
      "high24h": 2837655,
      "low24h": 2689949
    },
    {
      "id": "ethereum",
      "symbol": "ETH",
      "name": "Ethereum",
      "icon": "Ξ",
      "price": 89129,
      "priceUsd": 2829.4920634920636,
      "change24h": -3.51504,
      "marketCap": 10762552620275,
      "volume24h": 835924044187,
      "high24h": 95105,
      "low24h": 88104
    },
    {
      "id": "binancecoin",
      "symbol": "BNB",
      "name": "BNB",
      "icon": "🔶",
      "price": 26226,
      "priceUsd": 832.5714285714286,
      "change24h": -3.085,
      "marketCap": 3613138962285,
      "volume24h": 79173664351,
      "high24h": 27492,
      "low24h": 26213
    },
    {
      "id": "ripple",
      "symbol": "XRP",
      "name": "XRP",
      "icon": "✕",
      "price": 57.96,
      "priceUsd": 1.84,
      "change24h": -3.98776,
      "marketCap": 3507601600420,
      "volume24h": 106395969570,
      "high24h": 62.36,
      "low24h": 57.99
    },
    {
      "id": "solana",
      "symbol": "SOL",
      "name": "Solana",
      "icon": "◎",
      "price": 3867.25,
      "priceUsd": 122.76984126984127,
      "change24h": -3.89131,
      "marketCap": 2173491293682,
      "volume24h": 187835693913,
      "high24h": 4196.74,
      "low24h": 3835.18
    },
    {
      "id": "dogecoin",
      "symbol": "DOGE",
      "name": "Dogecoin",
      "icon": "🐕",
      "price": 3.92,
      "priceUsd": 0.12444444444444444,
      "change24h": -4.89347,
      "marketCap": 596517827030,
      "volume24h": 43404093631,
      "high24h": 4.27,
      "low24h": 3.92
    },
    {
      "id": "cardano",
      "symbol": "ADA",
      "name": "Cardano",
      "icon": "₳",
      "price": 11.41,
      "priceUsd": 0.3622222222222222,
      "change24h": -4.67901,
      "marketCap": 418467969115,
      "volume24h": 20936480492,
      "high24h": 12.53,
      "low24h": 11.41
    },
    {
      "id": "chainlink",
      "symbol": "LINK",
      "name": "Chainlink",
      "icon": "⬡",
      "price": 381.81,
      "priceUsd": 12.120952380952382,
      "change24h": -4.89697,
      "marketCap": 266325430184,
      "volume24h": 20691316070,
      "high24h": 411.79,
      "low24h": 381.82
    },
    {
      "id": "avalanche-2",
      "symbol": "AVAX",
      "name": "Avalanche",
      "icon": "🔺",
      "price": 367.87,
      "priceUsd": 11.678412698412698,
      "change24h": -3.76672,
      "marketCap": 157997809801,
      "volume24h": 12535533316,
      "high24h": 395.03,
      "low24h": 367.91
    },
    {
      "id": "polkadot",
      "symbol": "DOT",
      "name": "Polkadot",
      "icon": "●",
      "price": 56.06,
      "priceUsd": 1.7796825396825398,
      "change24h": -5.04528,
      "marketCap": 92299074596,
      "volume24h": 6110207636,
      "high24h": 61.16,
      "low24h": 56.08
    }
  ]
}